stroke_maps/__init__.py
stroke_maps/catchment.py
stroke_maps/catchment_class.py
stroke_maps/combine.py
stroke_maps/data.py
stroke_maps/geo.py
stroke_maps/geo_old.py
stroke_maps/import.py
stroke_maps/load_data.py
stroke_maps/model.py
stroke_maps/pathway.py
stroke_maps/patient.py
stroke_maps/plot.py
stroke_maps/plot_functions.py
stroke_maps/replication.py
stroke_maps/scenario.py
stroke_maps/setup.py
stroke_maps/units.py
stroke_maps/utils.py
stroke_maps/data/LHB.geojson
stroke_maps/data/LSOA.geojson
stroke_maps/data/SICBL.geojson
stroke_maps/data/admissions_2017-2019.csv
stroke_maps/data/ambulance_catchment_2021.geojson
stroke_maps/data/ambulance_catchment_2022.geojson
stroke_maps/data/ambulance_service_names.csv
stroke_maps/data/ccg15_amb.csv
stroke_maps/data/inter_hospital_time_calibrated.csv
stroke_maps/data/lsoa_ambo_lookup.csv
stroke_maps/data/lsoa_travel_time_matrix_calibrated.csv
stroke_maps/data/outline_England.geojson
stroke_maps/data/outline_EnglandWales.geojson
stroke_maps/data/outline_Wales.geojson
stroke_maps/data/outline_isdn.geojson
stroke_maps/data/regions_ew.csv
stroke_maps/data/regions_lsoa_ew.csv
stroke_maps/data/stroke_units_regions.csv
stroke_maps/data/unit_postcodes_coords.csv
stroke_maps/data_ni/OSNI_Open_Data_-_50K_Boundaries_-_NI_Counties.geojson
stroke_maps/data_ni/OSNI_Open_Data_-_50K_Boundaries_-_NI_Outline.geojson
stroke_maps/data_ni/admissions_2018.csv
stroke_maps/data_ni/hospital_coords.csv
stroke_maps/data_ni/hospitals.csv
stroke_maps/data_ni/inter_hospital_time.csv
stroke_maps/data_ni/sa2011.json
stroke_maps/data_ni/travel_matrix.csv
stroke_maps-0.5.3.dist-info/LICENSE
stroke_maps-0.5.3.dist-info/METADATA
stroke_maps-0.5.3.dist-info/WHEEL
stroke_maps-0.5.3.dist-info/top_level.txt
stroke_maps-0.5.3.dist-info/RECORD
