Metadata-Version: 2.1
Name: stroke-maps
Version: 0.5.3
Summary: Stroke modelling: package for maps of stroke units and LSOAs.
Home-page: https://github.com/stroke-modelling/stroke-maps
Author: Anna Laws
Author-email: a.laws2@exeter.ac.uk
License: MIT License (MIT)
Classifier: Programming Language :: Python :: 3.8
Classifier: Programming Language :: Python :: 3.9
Classifier: Programming Language :: Python :: 3.10
Classifier: Programming Language :: Python :: 3.11
Classifier: License :: OSI Approved :: MIT License
Classifier: Operating System :: OS Independent
Requires-Python: >=3.7.17
License-File: LICENSE
Requires-Dist: numpy >=1.20.0
Requires-Dist: pandas >=1.4.0
Requires-Dist: importlib-resources
